dlg_lowpass_components/__init__.py
dlg_lowpass_components/__main__.py
dlg_lowpass_components/filters.py
dlg_lowpass_components/generators.py
dlg_lowpass_components/utils.py
dlg_lowpass_components-0.2.dist-info/LICENSE
dlg_lowpass_components-0.2.dist-info/METADATA
dlg_lowpass_components-0.2.dist-info/WHEEL
dlg_lowpass_components-0.2.dist-info/entry_points.txt
dlg_lowpass_components-0.2.dist-info/top_level.txt
dlg_lowpass_components-0.2.dist-info/RECORD
