Metadata-Version: 2.1
Name: dlg-lowpass-components
Version: 0.2
Summary: Awesome dlg_lowpass_components created by pritchardn
Home-page: https://github.com/pritchardn/dlg_lowpass_components/
Author: pritchardn
Author-email: nicholas.pritchard@uwa.edu.au
License-File: LICENSE
Requires-Dist: daliuge-engine (>=2.0)
Requires-Dist: daliuge-translator (>=2.0)
Requires-Dist: numpy (==1.22.3)
Requires-Dist: pycuda (==2021.1)
Requires-Dist: pyFFTW (==0.13.0)
Requires-Dist: scikit-cuda (==0.5.3)
Provides-Extra: test
Requires-Dist: pytest ; extra == 'test'
Requires-Dist: coverage ; extra == 'test'
Requires-Dist: flake8 ; extra == 'test'
Requires-Dist: black ; extra == 'test'
Requires-Dist: isort ; extra == 'test'
Requires-Dist: pytest-cov ; extra == 'test'
Requires-Dist: codecov ; extra == 'test'
Requires-Dist: mypy ; extra == 'test'
Requires-Dist: gitchangelog ; extra == 'test'
Requires-Dist: mkdocs ; extra == 'test'
Requires-Dist: numpy (==1.22.3) ; extra == 'test'
Requires-Dist: pycuda (==2021.1) ; extra == 'test'
Requires-Dist: pyFFTW (==0.13.0) ; extra == 'test'
Requires-Dist: scikit-cuda (==0.5.3) ; extra == 'test'
